TensorConvolutionPlus/FA_Estimator.py
TensorConvolutionPlus/__init__.py
TensorConvolutionPlus/accuracy_estimation.py
TensorConvolutionPlus/conv_simulations.py
TensorConvolutionPlus/data_sampler.py
TensorConvolutionPlus/json_reader.py
TensorConvolutionPlus/main.py
TensorConvolutionPlus/monte_carlo.py
TensorConvolutionPlus/opf.py
TensorConvolutionPlus/plotting.py
TensorConvolutionPlus/scenario_setup.py
TensorConvolutionPlus/utils.py
TensorConvolutionPlus-0.1.1.dist-info/LICENSE
TensorConvolutionPlus-0.1.1.dist-info/METADATA
TensorConvolutionPlus-0.1.1.dist-info/WHEEL
TensorConvolutionPlus-0.1.1.dist-info/top_level.txt
TensorConvolutionPlus-0.1.1.dist-info/RECORD
