Metadata-Version: 2.2
Name: TensorConvolutionPlus
Version: 0.1.1
Summary: A package for TensorConvolution+ distribution network aggregated flexibility area estimation
Author-email: Demetris Chrysostomou <d.chrysostomou@tudelft.nl>
Project-URL: Homepage, https://demetris-ch.github.io/TensorConvolutionFlexibility/
Project-URL: Issues, https://github.com/Demetris-Ch/TensorConvolutionFlexibility
Classifier: Programming Language :: Python :: 3
Classifier: License :: OSI Approved :: MIT License
Classifier: Operating System :: OS Independent
Requires-Python: >=3.10
License-File: LICENSE
Requires-Dist: matplotlib>=3.8.2
Requires-Dist: networkx>=3.1
Requires-Dist: numpy>=1.24.3
Requires-Dist: pandapower>=2.13.1
Requires-Dist: pandas>=1.5.3
Requires-Dist: scikit-learn>=1.3.0
Requires-Dist: scipy>=1.11.2
Requires-Dist: seaborn>=0.13.2
Requires-Dist: tntorch>=1.1.1
Requires-Dist: torch>=2.0.1
Requires-Dist: tqdm>=4.66.1
